{"v":"5.9.4","fr":24,"ip":0,"op":217,"w":1920,"h":1440,"nm":"Modualtion Aniamtion V2","ddd":0,"assets":[],"layers":[{"ddd":0,"ind":1,"ty":3,"nm":"Null 1","sr":1,"ks":{"o":{"a":0,"k":0,"ix":11},"r":{"a":0,"k":0,"ix":10},"p":{"a":1,"k":[{"i":{"x":0.261,"y":1},"o":{"x":0.735,"y":0},"t":136,"s":[960,720,0],"to":[-80.3,-59.033,0],"ti":[80.3,59.033,0]},{"i":{"x":0.667,"y":0.667},"o":{"x":0.167,"y":0.167},"t":147,"s":[478.2,365.8,0],"to":[0,0,0],"ti":[0,0,0]},{"i":{"x":0.261,"y":1},"o":{"x":0.735,"y":0},"t":206,"s":[478.2,365.8,0],"to":[80.3,59.033,0],"ti":[-80.3,-59.033,0]},{"t":217,"s":[960,720,0]}],"ix":2,"l":2},"a":{"a":0,"k":[0,0,0],"ix":1,"l":2},"s":{"a":1,"k":[{"i":{"x":[0.261,0.277,0.667],"y":[1,1,1]},"o":{"x":[0.735,0.727,0.333],"y":[0,0,0]},"t":136,"s":[110,110,100]},{"i":{"x":[0.667,0.667,0.667],"y":[1,1,1]},"o":{"x":[0.167,0.167,0.167],"y":[0,0,0]},"t":147,"s":[71.5,71.5,100]},{"i":{"x":[0.261,0.277,0.667],"y":[1,1,1]},"o":{"x":[0.735,0.727,0.333],"y":[0,0,0]},"t":206,"s":[71.5,71.5,100]},{"t":217,"s":[110,110,100]}],"ix":6,"l":2}},"ao":0,"ip":0,"op":217,"st":0,"bm":0},{"ddd":0,"ind":2,"ty":4,"nm":"Bar3","parent":3,"sr":1,"ks":{"o":{"a":0,"k":100,"ix":11},"r":{"a":0,"k":0,"ix":10},"p":{"a":1,"k":[{"i":{"x":0.261,"y":1},"o":{"x":0.735,"y":0},"t":30,"s":[-60.319,267.694,0],"to":[0,2.906,0],"ti":[0,-2.906,0]},{"i":{"x":0.667,"y":0.667},"o":{"x":0.333,"y":0.333},"t":37,"s":[-60.319,285.128,0],"to":[0,0,0],"ti":[0,0,0]},{"i":{"x":0.261,"y":1},"o":{"x":0.735,"y":0},"t":64,"s":[-60.319,285.128,0],"to":[0,-1.93,0],"ti":[0,1.93,0]},{"i":{"x":0.667,"y":0.667},"o":{"x":0.333,"y":0.333},"t":71,"s":[-60.319,273.549,0],"to":[0,0,0],"ti":[0,0,0]},{"i":{"x":0.261,"y":1},"o":{"x":0.735,"y":0},"t":99,"s":[-60.319,273.549,0],"to":[0,3.167,0],"ti":[0,-3.167,0]},{"i":{"x":0.667,"y":0.667},"o":{"x":0.333,"y":0.333},"t":107,"s":[-60.319,292.549,0],"to":[0,0,0],"ti":[0,0,0]},{"i":{"x":0.261,"y":1},"o":{"x":0.735,"y":0},"t":136,"s":[-60.319,292.549,0],"to":[-1.5,-3.5,0],"ti":[1.5,3.5,0]},{"i":{"x":0.667,"y":0.667},"o":{"x":0.167,"y":0.167},"t":147,"s":[-69.319,271.549,0],"to":[0,0,0],"ti":[0,0,0]},{"i":{"x":0.261,"y":1},"o":{"x":0.735,"y":0},"t":206,"s":[-69.319,271.549,0],"to":[1.5,-0.642,0],"ti":[-1.5,0.642,0]},{"t":217,"s":[-60.319,267.694,0]}],"ix":2,"l":2},"a":{"a":0,"k":[-8.5,166.125,0],"ix":1,"l":2},"s":{"a":1,"k":[{"i":{"x":[0.261,0.277,0.667],"y":[1,1,1]},"o":{"x":[0.735,0.719,0.333],"y":[0,0,0]},"t":30,"s":[100,100,100]},{"i":{"x":[0.667,0.667,0.667],"y":[1,1,1]},"o":{"x":[0.333,0.333,0.333],"y":[0,0,0]},"t":37,"s":[82,64,100]},{"i":{"x":[0.261,0.277,0.667],"y":[1,1,1]},"o":{"x":[0.735,0.727,0.333],"y":[0,0,0]},"t":64,"s":[82,64,100]},{"i":{"x":[0.667,0.667,0.667],"y":[1,1,1]},"o":{"x":[0.333,0.333,0.333],"y":[0,0,0]},"t":71,"s":[122,73,100]},{"i":{"x":[0.261,0.277,0.667],"y":[1,1,1]},"o":{"x":[0.735,0.727,0.333],"y":[0,0,0]},"t":99,"s":[122,73,100]},{"i":{"x":[0.667,0.667,0.667],"y":[1,1,1]},"o":{"x":[0.333,0.333,0.333],"y":[0,0,0]},"t":107,"s":[122,42,100]},{"i":{"x":[0.261,0.277,0.667],"y":[1,1,1]},"o":{"x":[0.735,0.727,0.333],"y":[0,0,0]},"t":136,"s":[122,42,100]},{"i":{"x":[0.667,0.667,0.667],"y":[1,1,1]},"o":{"x":[0.167,0.167,0.167],"y":[0,0,0]},"t":147,"s":[124,96,100]},{"i":{"x":[0.261,0.277,0.667],"y":[1,1,1]},"o":{"x":[0.735,0.727,0.333],"y":[0,0,0]},"t":206,"s":[124,96,100]},{"t":217,"s":[100,100,100]}],"ix":6,"l":2}},"ao":0,"shapes":[{"ty":"gr","it":[{"ind":0,"ty":"sh","ix":1,"ks":{"a":1,"k":[{"i":{"x":0.849,"y":1},"o":{"x":0.167,"y":0.167},"t":2,"s":[{"i":[[0,0],[0,0]],"o":[[0,0],[0,0]],"v":[[-421,166],[404,166]],"c":false}]},{"i":{"x":0.261,"y":1},"o":{"x":0.735,"y":0},"t":30,"s":[{"i":[[0,0],[0,0]],"o":[[0,0],[0,0]],"v":[[-421,166],[404,166]],"c":false}]},{"i":{"x":0.667,"y":1},"o":{"x":0.333,"y":0},"t":37,"s":[{"i":[[0,0],[0,0]],"o":[[0,0],[0,0]],"v":[[-538.256,164.222],[525.394,164.222]],"c":false}]},{"i":{"x":0.261,"y":1},"o":{"x":0.735,"y":0},"t":64,"s":[{"i":[[0,0],[0,0]],"o":[[0,0],[0,0]],"v":[[-538.256,164.222],[525.394,164.222]],"c":false}]},{"i":{"x":0.667,"y":1},"o":{"x":0.333,"y":0},"t":71,"s":[{"i":[[0,0],[0,0]],"o":[[0,0],[0,0]],"v":[[-334.946,163.95],[333.807,163.95]],"c":false}]},{"i":{"x":0.261,"y":1},"o":{"x":0.735,"y":0},"t":206,"s":[{"i":[[0,0],[0,0]],"o":[[0,0],[0,0]],"v":[[-334.946,163.95],[333.807,163.95]],"c":false}]},{"t":217,"s":[{"i":[[0,0],[0,0]],"o":[[0,0],[0,0]],"v":[[-421,166],[404,166]],"c":false}]}],"ix":2},"nm":"Path 1","mn":"ADBE Vector Shape - Group","hd":false},{"ty":"st","c":{"a":0,"k":[1,0.36862745098,0.392156862745,1],"ix":3},"o":{"a":0,"k":100,"ix":4},"w":{"a":1,"k":[{"i":{"x":[0.613],"y":[1]},"o":{"x":[0.276],"y":[0]},"t":30,"s":[35]},{"i":{"x":[0.682],"y":[1]},"o":{"x":[0.223],"y":[0]},"t":37,"s":[32]},{"i":{"x":[0.261],"y":[1]},"o":{"x":[0.735],"y":[0]},"t":136,"s":[32]},{"i":{"x":[0.667],"y":[1]},"o":{"x":[0.167],"y":[0]},"t":147,"s":[25]},{"i":{"x":[0.261],"y":[1]},"o":{"x":[0.735],"y":[0]},"t":206,"s":[25]},{"t":217,"s":[35]}],"ix":5},"lc":2,"lj":2,"bm":0,"nm":"Stroke 1","mn":"ADBE Vector Graphic - Stroke","hd":false},{"ty":"tr","p":{"a":0,"k":[0,0],"ix":2},"a":{"a":0,"k":[0,0],"ix":1},"s":{"a":0,"k":[100,100],"ix":3},"r":{"a":0,"k":0,"ix":6},"o":{"a":0,"k":100,"ix":7},"sk":{"a":0,"k":0,"ix":4},"sa":{"a":0,"k":0,"ix":5},"nm":"Transform"}],"nm":"Shape 1","np":2,"cix":2,"bm":0,"ix":1,"mn":"ADBE Vector Group","hd":false},{"ty":"tm","s":{"a":0,"k":0,"ix":1},"e":{"a":1,"k":[{"i":{"x":[0.667],"y":[1]},"o":{"x":[0.167],"y":[0.167]},"t":2,"s":[1]},{"i":{"x":[0.261],"y":[1]},"o":{"x":[0.735],"y":[0]},"t":136,"s":[100]},{"i":{"x":[0.833],"y":[1]},"o":{"x":[0.333],"y":[0]},"t":147,"s":[1]},{"i":{"x":[0.833],"y":[0.833]},"o":{"x":[0.161],"y":[0.143]},"t":148,"s":[1]},{"i":{"x":[0.667],"y":[1]},"o":{"x":[0.167],"y":[0.167]},"t":205,"s":[62.411]},{"i":{"x":[0.261],"y":[1]},"o":{"x":[0.735],"y":[0]},"t":206,"s":[63.491]},{"i":{"x":[0.829],"y":[1]},"o":{"x":[0.167],"y":[0]},"t":216,"s":[1]},{"t":251,"s":[100]}],"ix":2},"o":{"a":0,"k":0,"ix":3},"m":1,"ix":2,"nm":"Trim Paths 1","mn":"ADBE Vector Filter - Trim","hd":false}],"ip":0,"op":217,"st":-142,"ct":1,"bm":0},{"ddd":0,"ind":3,"ty":4,"nm":"Shape3","parent":1,"sr":1,"ks":{"o":{"a":0,"k":100,"ix":11},"r":{"a":0,"k":0,"ix":10},"p":{"a":0,"k":[0,0,0],"ix":2,"l":2},"a":{"a":0,"k":[-60.319,50.569,0],"ix":1,"l":2},"s":{"a":1,"k":[{"i":{"x":[0.261,0.277,0.667],"y":[1,1,1]},"o":{"x":[0.735,0.727,0.333],"y":[0,0,0]},"t":30,"s":[100,100,100]},{"i":{"x":[0.667,0.667,0.667],"y":[1,1,1]},"o":{"x":[0.333,0.333,0.333],"y":[0,0,0]},"t":37,"s":[125,166,100]},{"i":{"x":[0.261,0.277,0.667],"y":[1,1,1]},"o":{"x":[0.735,0.727,0.333],"y":[0,0,0]},"t":64,"s":[125,166,100]},{"i":{"x":[0.667,0.667,0.667],"y":[1,1,1]},"o":{"x":[0.333,0.333,0.333],"y":[0,0,0]},"t":71,"s":[54,95,100]},{"i":{"x":[0.261,0.277,0.667],"y":[1,1,1]},"o":{"x":[0.735,0.727,0.333],"y":[0,0,0]},"t":99,"s":[54,95,100]},{"i":{"x":[0.667,0.667,0.667],"y":[1,1,1]},"o":{"x":[0.333,0.333,0.333],"y":[0,0,0]},"t":107,"s":[61,181,100]},{"i":{"x":[0.261,0.277,0.667],"y":[1,1,1]},"o":{"x":[0.735,0.727,0.333],"y":[0,0,0]},"t":136,"s":[61,181,100]},{"i":{"x":[0.667,0.667,0.667],"y":[1,1,1]},"o":{"x":[0.167,0.167,0.167],"y":[0,0,0]},"t":147,"s":[100,127,100]},{"i":{"x":[0.261,0.277,0.667],"y":[1,1,1]},"o":{"x":[0.735,0.727,0.333],"y":[0,0,0]},"t":206,"s":[100,127,100]},{"t":217,"s":[100,100,100]}],"ix":6,"l":2}},"ao":0,"ef":[{"ty":25,"nm":"Drop Shadow","np":8,"mn":"ADBE Drop Shadow","ix":1,"en":1,"ef":[{"ty":2,"nm":"Shadow Color","mn":"ADBE Drop Shadow-0001","ix":1,"v":{"a":0,"k":[0,0,0,1],"ix":1}},{"ty":0,"nm":"Opacity","mn":"ADBE Drop Shadow-0002","ix":2,"v":{"a":0,"k":55.5,"ix":2}},{"ty":0,"nm":"Direction","mn":"ADBE Drop Shadow-0003","ix":3,"v":{"a":0,"k":135,"ix":3}},{"ty":0,"nm":"Distance","mn":"ADBE Drop Shadow-0004","ix":4,"v":{"a":0,"k":4,"ix":4}},{"ty":0,"nm":"Softness","mn":"ADBE Drop Shadow-0005","ix":5,"v":{"a":0,"k":10,"ix":5}},{"ty":7,"nm":"Shadow Only","mn":"ADBE Drop Shadow-0006","ix":6,"v":{"a":0,"k":0,"ix":6}}]}],"shapes":[{"ty":"gr","it":[{"ty":"rc","d":1,"s":{"a":0,"k":[960,540],"ix":2},"p":{"a":1,"k":[{"t":0,"s":[0,0],"h":1},{"i":{"x":0.261,"y":0.261},"o":{"x":0.735,"y":0.735},"t":136,"s":[0,0],"to":[0,0],"ti":[0,0]},{"i":{"x":0.667,"y":0.667},"o":{"x":0.167,"y":0.167},"t":147,"s":[0,0],"to":[0,0],"ti":[0,0]},{"i":{"x":0.261,"y":0.261},"o":{"x":0.735,"y":0.735},"t":206,"s":[0,0],"to":[0,0],"ti":[0,0]},{"t":217,"s":[0,0]}],"ix":3},"r":{"a":0,"k":14,"ix":4},"nm":"Rectangle Path 1","mn":"ADBE Vector Shape - Rect","hd":false},{"ty":"fl","c":{"a":0,"k":[0,0.317647058824,0.454901960784,1],"ix":4},"o":{"a":0,"k":100,"ix":5},"r":1,"bm":0,"nm":"Fill 1","mn":"ADBE Vector Graphic - Fill","hd":false},{"ty":"tr","p":{"a":0,"k":[-60.319,50.569],"ix":2},"a":{"a":0,"k":[0,0],"ix":1},"s":{"a":0,"k":[100,100],"ix":3},"r":{"a":0,"k":0,"ix":6},"o":{"a":0,"k":100,"ix":7},"sk":{"a":0,"k":0,"ix":4},"sa":{"a":0,"k":0,"ix":5},"nm":"Transform"}],"nm":"Rectangle 1","np":3,"cix":2,"bm":0,"ix":1,"mn":"ADBE Vector Group","hd":false}],"ip":0,"op":217,"st":0,"ct":1,"bm":0},{"ddd":0,"ind":4,"ty":3,"nm":"Null 1","sr":1,"ks":{"o":{"a":0,"k":0,"ix":11},"r":{"a":0,"k":0,"ix":10},"p":{"a":1,"k":[{"i":{"x":0.261,"y":1},"o":{"x":0.735,"y":0},"t":136,"s":[960,720,0],"to":[109.633,53.35,0],"ti":[-109.633,-53.35,0]},{"i":{"x":0.667,"y":0.667},"o":{"x":0.167,"y":0.167},"t":147,"s":[1617.8,1040.1,0],"to":[0,0,0],"ti":[0,0,0]},{"i":{"x":0.261,"y":1},"o":{"x":0.735,"y":0},"t":206,"s":[1617.8,1040.1,0],"to":[-109.633,-53.35,0],"ti":[109.633,53.35,0]},{"t":217,"s":[960,720,0]}],"ix":2,"l":2},"a":{"a":0,"k":[0,0,0],"ix":1,"l":2},"s":{"a":1,"k":[{"i":{"x":[0.261,0.277,0.667],"y":[1,1,1]},"o":{"x":[0.735,0.727,0.333],"y":[0,0,0]},"t":136,"s":[110,110,100]},{"i":{"x":[0.667,0.667,0.667],"y":[1,1,1]},"o":{"x":[0.167,0.167,0.167],"y":[0,0,0]},"t":147,"s":[71.5,71.5,100]},{"i":{"x":[0.261,0.277,0.667],"y":[1,1,1]},"o":{"x":[0.735,0.727,0.333],"y":[0,0,0]},"t":206,"s":[71.5,71.5,100]},{"t":217,"s":[110,110,100]}],"ix":6,"l":2}},"ao":0,"ip":0,"op":217,"st":0,"bm":0},{"ddd":0,"ind":5,"ty":4,"nm":"Bar4","parent":6,"sr":1,"ks":{"o":{"a":0,"k":100,"ix":11},"r":{"a":0,"k":0,"ix":10},"p":{"a":1,"k":[{"i":{"x":0.261,"y":1},"o":{"x":0.735,"y":0},"t":30,"s":[-60.319,267.694,0],"to":[0,2.906,0],"ti":[0,-2.906,0]},{"i":{"x":0.667,"y":0.667},"o":{"x":0.333,"y":0.333},"t":37,"s":[-60.319,285.128,0],"to":[0,0,0],"ti":[0,0,0]},{"i":{"x":0.261,"y":1},"o":{"x":0.735,"y":0},"t":64,"s":[-60.319,285.128,0],"to":[0,-1.93,0],"ti":[0,1.93,0]},{"i":{"x":0.667,"y":0.667},"o":{"x":0.333,"y":0.333},"t":71,"s":[-60.319,273.549,0],"to":[0,0,0],"ti":[0,0,0]},{"i":{"x":0.261,"y":1},"o":{"x":0.735,"y":0},"t":99,"s":[-60.319,273.549,0],"to":[0,3.167,0],"ti":[0,-3.167,0]},{"i":{"x":0.667,"y":0.667},"o":{"x":0.333,"y":0.333},"t":107,"s":[-60.319,292.549,0],"to":[0,0,0],"ti":[0,0,0]},{"i":{"x":0.667,"y":0.667},"o":{"x":0.735,"y":0.735},"t":136,"s":[-60.319,292.549,0],"to":[0,0,0],"ti":[0,0,0]},{"i":{"x":0.261,"y":1},"o":{"x":0.735,"y":0},"t":206,"s":[-60.319,292.549,0],"to":[0,-4.142,0],"ti":[0,4.142,0]},{"t":217,"s":[-60.319,267.694,0]}],"ix":2,"l":2},"a":{"a":0,"k":[-8.5,166.125,0],"ix":1,"l":2},"s":{"a":1,"k":[{"i":{"x":[0.261,0.277,0.667],"y":[1,1,1]},"o":{"x":[0.735,0.719,0.333],"y":[0,0,0]},"t":30,"s":[100,100,100]},{"i":{"x":[0.667,0.667,0.667],"y":[1,1,1]},"o":{"x":[0.333,0.333,0.333],"y":[0,0,0]},"t":37,"s":[82,64,100]},{"i":{"x":[0.261,0.277,0.667],"y":[1,1,1]},"o":{"x":[0.735,0.727,0.333],"y":[0,0,0]},"t":64,"s":[82,64,100]},{"i":{"x":[0.667,0.667,0.667],"y":[1,1,1]},"o":{"x":[0.333,0.333,0.333],"y":[0,0,0]},"t":71,"s":[122,73,100]},{"i":{"x":[0.261,0.277,0.667],"y":[1,1,1]},"o":{"x":[0.735,0.727,0.333],"y":[0,0,0]},"t":99,"s":[122,73,100]},{"i":{"x":[0.667,0.667,0.667],"y":[1,1,1]},"o":{"x":[0.333,0.333,0.333],"y":[0,0,0]},"t":107,"s":[122,42,100]},{"i":{"x":[0.667,0.667,0.667],"y":[1,1,1]},"o":{"x":[0.735,0.727,0.333],"y":[0,0,0]},"t":136,"s":[122,42,100]},{"i":{"x":[0.261,0.277,0.667],"y":[1,1,1]},"o":{"x":[0.735,0.727,0.333],"y":[0,0,0]},"t":206,"s":[122,42,100]},{"t":217,"s":[100,100,100]}],"ix":6,"l":2}},"ao":0,"shapes":[{"ty":"gr","it":[{"ind":0,"ty":"sh","ix":1,"ks":{"a":1,"k":[{"i":{"x":0.849,"y":1},"o":{"x":0.167,"y":0.167},"t":2,"s":[{"i":[[0,0],[0,0]],"o":[[0,0],[0,0]],"v":[[-421,166],[404,166]],"c":false}]},{"i":{"x":0.261,"y":1},"o":{"x":0.735,"y":0},"t":30,"s":[{"i":[[0,0],[0,0]],"o":[[0,0],[0,0]],"v":[[-421,166],[404,166]],"c":false}]},{"i":{"x":0.667,"y":1},"o":{"x":0.333,"y":0},"t":37,"s":[{"i":[[0,0],[0,0]],"o":[[0,0],[0,0]],"v":[[-538.256,164.222],[525.394,164.222]],"c":false}]},{"i":{"x":0.261,"y":1},"o":{"x":0.735,"y":0},"t":64,"s":[{"i":[[0,0],[0,0]],"o":[[0,0],[0,0]],"v":[[-538.256,164.222],[525.394,164.222]],"c":false}]},{"i":{"x":0.667,"y":1},"o":{"x":0.333,"y":0},"t":71,"s":[{"i":[[0,0],[0,0]],"o":[[0,0],[0,0]],"v":[[-334.946,163.95],[333.807,163.95]],"c":false}]},{"i":{"x":0.261,"y":1},"o":{"x":0.735,"y":0},"t":206,"s":[{"i":[[0,0],[0,0]],"o":[[0,0],[0,0]],"v":[[-334.946,163.95],[333.807,163.95]],"c":false}]},{"t":217,"s":[{"i":[[0,0],[0,0]],"o":[[0,0],[0,0]],"v":[[-421,166],[404,166]],"c":false}]}],"ix":2},"nm":"Path 1","mn":"ADBE Vector Shape - Group","hd":false},{"ty":"st","c":{"a":0,"k":[1,0.36862745098,0.392156862745,1],"ix":3},"o":{"a":0,"k":100,"ix":4},"w":{"a":1,"k":[{"i":{"x":[0.613],"y":[1]},"o":{"x":[0.276],"y":[0]},"t":30,"s":[35]},{"i":{"x":[0.682],"y":[1]},"o":{"x":[0.223],"y":[0]},"t":37,"s":[32]},{"i":{"x":[0.667],"y":[1]},"o":{"x":[0.735],"y":[0]},"t":136,"s":[32]},{"i":{"x":[0.261],"y":[1]},"o":{"x":[0.735],"y":[0]},"t":206,"s":[32]},{"t":217,"s":[35]}],"ix":5},"lc":2,"lj":2,"bm":0,"nm":"Stroke 1","mn":"ADBE Vector Graphic - Stroke","hd":false},{"ty":"tr","p":{"a":0,"k":[0,0],"ix":2},"a":{"a":0,"k":[0,0],"ix":1},"s":{"a":0,"k":[100,100],"ix":3},"r":{"a":0,"k":0,"ix":6},"o":{"a":0,"k":100,"ix":7},"sk":{"a":0,"k":0,"ix":4},"sa":{"a":0,"k":0,"ix":5},"nm":"Transform"}],"nm":"Shape 1","np":2,"cix":2,"bm":0,"ix":1,"mn":"ADBE Vector Group","hd":false},{"ty":"tm","s":{"a":0,"k":0,"ix":1},"e":{"a":1,"k":[{"i":{"x":[0.833],"y":[0.833]},"o":{"x":[0.167],"y":[0.167]},"t":2,"s":[1]},{"i":{"x":[0.261],"y":[1]},"o":{"x":[0.167],"y":[0.167]},"t":136,"s":[100]},{"i":{"x":[0.833],"y":[1]},"o":{"x":[0.333],"y":[0]},"t":147,"s":[1]},{"i":{"x":[0.833],"y":[0.833]},"o":{"x":[0.163],"y":[0.143]},"t":148,"s":[1]},{"i":{"x":[0.634],"y":[0.624]},"o":{"x":[0.299],"y":[0.289]},"t":205,"s":[63.491]},{"i":{"x":[0.609],"y":[1.064]},"o":{"x":[0.27],"y":[-0.041]},"t":206,"s":[64.313]},{"i":{"x":[0.837],"y":[1]},"o":{"x":[0.281],"y":[0.09]},"t":217,"s":[4]},{"t":251,"s":[100]}],"ix":2},"o":{"a":0,"k":0,"ix":3},"m":1,"ix":2,"nm":"Trim Paths 1","mn":"ADBE Vector Filter - Trim","hd":false}],"ip":0,"op":217,"st":-142,"ct":1,"bm":0},{"ddd":0,"ind":6,"ty":4,"nm":"Shape4","parent":4,"sr":1,"ks":{"o":{"a":0,"k":100,"ix":11},"r":{"a":0,"k":0,"ix":10},"p":{"a":0,"k":[0,0,0],"ix":2,"l":2},"a":{"a":0,"k":[-60.319,50.569,0],"ix":1,"l":2},"s":{"a":1,"k":[{"i":{"x":[0.261,0.277,0.667],"y":[1,1,1]},"o":{"x":[0.735,0.727,0.333],"y":[0,0,0]},"t":30,"s":[100,100,100]},{"i":{"x":[0.667,0.667,0.667],"y":[1,1,1]},"o":{"x":[0.333,0.333,0.333],"y":[0,0,0]},"t":37,"s":[125,166,100]},{"i":{"x":[0.261,0.277,0.667],"y":[1,1,1]},"o":{"x":[0.735,0.727,0.333],"y":[0,0,0]},"t":64,"s":[125,166,100]},{"i":{"x":[0.667,0.667,0.667],"y":[1,1,1]},"o":{"x":[0.333,0.333,0.333],"y":[0,0,0]},"t":71,"s":[54,95,100]},{"i":{"x":[0.261,0.277,0.667],"y":[1,1,1]},"o":{"x":[0.735,0.727,0.333],"y":[0,0,0]},"t":99,"s":[54,95,100]},{"i":{"x":[0.667,0.667,0.667],"y":[1,1,1]},"o":{"x":[0.333,0.333,0.333],"y":[0,0,0]},"t":107,"s":[61,181,100]},{"i":{"x":[0.667,0.667,0.667],"y":[1,1,1]},"o":{"x":[0.735,0.727,0.333],"y":[0,0,0]},"t":136,"s":[61,181,100]},{"i":{"x":[0.261,0.277,0.667],"y":[1,1,1]},"o":{"x":[0.735,0.727,0.333],"y":[0,0,0]},"t":206,"s":[61,181,100]},{"t":217,"s":[100,100,100]}],"ix":6,"l":2}},"ao":0,"ef":[{"ty":25,"nm":"Drop Shadow","np":8,"mn":"ADBE Drop Shadow","ix":1,"en":1,"ef":[{"ty":2,"nm":"Shadow Color","mn":"ADBE Drop Shadow-0001","ix":1,"v":{"a":0,"k":[0,0,0,1],"ix":1}},{"ty":0,"nm":"Opacity","mn":"ADBE Drop Shadow-0002","ix":2,"v":{"a":0,"k":55.5,"ix":2}},{"ty":0,"nm":"Direction","mn":"ADBE Drop Shadow-0003","ix":3,"v":{"a":0,"k":135,"ix":3}},{"ty":0,"nm":"Distance","mn":"ADBE Drop Shadow-0004","ix":4,"v":{"a":0,"k":4,"ix":4}},{"ty":0,"nm":"Softness","mn":"ADBE Drop Shadow-0005","ix":5,"v":{"a":0,"k":10,"ix":5}},{"ty":7,"nm":"Shadow Only","mn":"ADBE Drop Shadow-0006","ix":6,"v":{"a":0,"k":0,"ix":6}}]}],"shapes":[{"ty":"gr","it":[{"ty":"rc","d":1,"s":{"a":0,"k":[960,540],"ix":2},"p":{"a":1,"k":[{"t":0,"s":[0,0],"h":1},{"i":{"x":0.667,"y":0.667},"o":{"x":0.735,"y":0.735},"t":136,"s":[0,0],"to":[0,0],"ti":[0,0]},{"i":{"x":0.261,"y":0.261},"o":{"x":0.735,"y":0.735},"t":206,"s":[0,0],"to":[0,0],"ti":[0,0]},{"t":217,"s":[0,0]}],"ix":3},"r":{"a":0,"k":14,"ix":4},"nm":"Rectangle Path 1","mn":"ADBE Vector Shape - Rect","hd":false},{"ty":"fl","c":{"a":0,"k":[0,0.317647058824,0.454901990704,1],"ix":4},"o":{"a":0,"k":100,"ix":5},"r":1,"bm":0,"nm":"Fill 1","mn":"ADBE Vector Graphic - Fill","hd":false},{"ty":"tr","p":{"a":0,"k":[-60.319,50.569],"ix":2},"a":{"a":0,"k":[0,0],"ix":1},"s":{"a":0,"k":[100,100],"ix":3},"r":{"a":0,"k":0,"ix":6},"o":{"a":0,"k":100,"ix":7},"sk":{"a":0,"k":0,"ix":4},"sa":{"a":0,"k":0,"ix":5},"nm":"Transform"}],"nm":"Rectangle 1","np":3,"cix":2,"bm":0,"ix":1,"mn":"ADBE Vector Group","hd":false}],"ip":0,"op":217,"st":0,"ct":1,"bm":0},{"ddd":0,"ind":7,"ty":3,"nm":"Null 1","sr":1,"ks":{"o":{"a":0,"k":0,"ix":11},"r":{"a":0,"k":0,"ix":10},"p":{"a":1,"k":[{"i":{"x":0.261,"y":1},"o":{"x":0.735,"y":0},"t":136,"s":[960,720,0],"to":[22.55,53.35,0],"ti":[-22.55,-53.35,0]},{"i":{"x":0.667,"y":0.667},"o":{"x":0.167,"y":0.167},"t":147,"s":[1095.3,1040.1,0],"to":[0,0,0],"ti":[0,0,0]},{"i":{"x":0.261,"y":1},"o":{"x":0.735,"y":0},"t":206,"s":[1095.3,1040.1,0],"to":[-22.55,-53.35,0],"ti":[22.55,53.35,0]},{"t":217,"s":[960,720,0]}],"ix":2,"l":2},"a":{"a":0,"k":[0,0,0],"ix":1,"l":2},"s":{"a":1,"k":[{"i":{"x":[0.261,0.277,0.667],"y":[1,1,1]},"o":{"x":[0.735,0.727,0.333],"y":[0,0,0]},"t":136,"s":[110,110,100]},{"i":{"x":[0.667,0.667,0.667],"y":[1,1,1]},"o":{"x":[0.167,0.167,0.167],"y":[0,0,0]},"t":147,"s":[71.5,71.5,100]},{"i":{"x":[0.261,0.277,0.667],"y":[1,1,1]},"o":{"x":[0.735,0.727,0.333],"y":[0,0,0]},"t":206,"s":[71.5,71.5,100]},{"t":217,"s":[110,110,100]}],"ix":6,"l":2}},"ao":0,"ip":0,"op":217,"st":0,"bm":0},{"ddd":0,"ind":8,"ty":4,"nm":"Bar5","parent":9,"sr":1,"ks":{"o":{"a":0,"k":100,"ix":11},"r":{"a":0,"k":0,"ix":10},"p":{"a":1,"k":[{"i":{"x":0.261,"y":1},"o":{"x":0.735,"y":0},"t":30,"s":[-60.319,267.694,0],"to":[0,2.906,0],"ti":[0,-2.906,0]},{"i":{"x":0.667,"y":0.667},"o":{"x":0.333,"y":0.333},"t":37,"s":[-60.319,285.128,0],"to":[0,0,0],"ti":[0,0,0]},{"i":{"x":0.261,"y":1},"o":{"x":0.735,"y":0},"t":64,"s":[-60.319,285.128,0],"to":[0,-1.93,0],"ti":[0,1.93,0]},{"i":{"x":0.667,"y":0.667},"o":{"x":0.333,"y":0.333},"t":71,"s":[-60.319,273.549,0],"to":[0,0,0],"ti":[0,0,0]},{"i":{"x":0.261,"y":1},"o":{"x":0.735,"y":0},"t":99,"s":[-60.319,273.549,0],"to":[0,3.167,0],"ti":[0,-3.167,0]},{"i":{"x":0.667,"y":0.667},"o":{"x":0.333,"y":0.333},"t":107,"s":[-60.319,292.549,0],"to":[0,0,0],"ti":[0,0,0]},{"i":{"x":0.261,"y":1},"o":{"x":0.735,"y":0},"t":136,"s":[-60.319,292.549,0],"to":[-1.5,-3.5,0],"ti":[1.5,3.5,0]},{"i":{"x":0.667,"y":0.667},"o":{"x":0.167,"y":0.167},"t":147,"s":[-69.319,271.549,0],"to":[0,0,0],"ti":[0,0,0]},{"i":{"x":0.261,"y":1},"o":{"x":0.735,"y":0},"t":206,"s":[-69.319,271.549,0],"to":[1.5,-0.642,0],"ti":[-1.5,0.642,0]},{"t":217,"s":[-60.319,267.694,0]}],"ix":2,"l":2},"a":{"a":0,"k":[-8.5,166.125,0],"ix":1,"l":2},"s":{"a":1,"k":[{"i":{"x":[0.261,0.277,0.667],"y":[1,1,1]},"o":{"x":[0.735,0.719,0.333],"y":[0,0,0]},"t":30,"s":[100,100,100]},{"i":{"x":[0.667,0.667,0.667],"y":[1,1,1]},"o":{"x":[0.333,0.333,0.333],"y":[0,0,0]},"t":37,"s":[82,64,100]},{"i":{"x":[0.261,0.277,0.667],"y":[1,1,1]},"o":{"x":[0.735,0.727,0.333],"y":[0,0,0]},"t":64,"s":[82,64,100]},{"i":{"x":[0.667,0.667,0.667],"y":[1,1,1]},"o":{"x":[0.333,0.333,0.333],"y":[0,0,0]},"t":71,"s":[122,73,100]},{"i":{"x":[0.261,0.277,0.667],"y":[1,1,1]},"o":{"x":[0.735,0.727,0.333],"y":[0,0,0]},"t":99,"s":[122,73,100]},{"i":{"x":[0.667,0.667,0.667],"y":[1,1,1]},"o":{"x":[0.333,0.333,0.333],"y":[0,0,0]},"t":107,"s":[122,42,100]},{"i":{"x":[0.261,0.277,0.667],"y":[1,1,1]},"o":{"x":[0.735,0.727,0.333],"y":[0,0,0]},"t":136,"s":[122,42,100]},{"i":{"x":[0.667,0.667,0.667],"y":[1,1,1]},"o":{"x":[0.167,0.167,0.167],"y":[0,0,0]},"t":147,"s":[124,87,100]},{"i":{"x":[0.261,0.277,0.667],"y":[1,1,1]},"o":{"x":[0.735,0.727,0.333],"y":[0,0,0]},"t":206,"s":[124,87,100]},{"t":217,"s":[100,100,100]}],"ix":6,"l":2}},"ao":0,"shapes":[{"ty":"gr","it":[{"ind":0,"ty":"sh","ix":1,"ks":{"a":1,"k":[{"i":{"x":0.849,"y":1},"o":{"x":0.167,"y":0.167},"t":2,"s":[{"i":[[0,0],[0,0]],"o":[[0,0],[0,0]],"v":[[-421,166],[404,166]],"c":false}]},{"i":{"x":0.261,"y":1},"o":{"x":0.735,"y":0},"t":30,"s":[{"i":[[0,0],[0,0]],"o":[[0,0],[0,0]],"v":[[-421,166],[404,166]],"c":false}]},{"i":{"x":0.667,"y":1},"o":{"x":0.333,"y":0},"t":37,"s":[{"i":[[0,0],[0,0]],"o":[[0,0],[0,0]],"v":[[-538.256,164.222],[525.394,164.222]],"c":false}]},{"i":{"x":0.261,"y":1},"o":{"x":0.735,"y":0},"t":64,"s":[{"i":[[0,0],[0,0]],"o":[[0,0],[0,0]],"v":[[-538.256,164.222],[525.394,164.222]],"c":false}]},{"i":{"x":0.667,"y":1},"o":{"x":0.333,"y":0},"t":71,"s":[{"i":[[0,0],[0,0]],"o":[[0,0],[0,0]],"v":[[-334.946,163.95],[333.807,163.95]],"c":false}]},{"i":{"x":0.261,"y":1},"o":{"x":0.735,"y":0},"t":206,"s":[{"i":[[0,0],[0,0]],"o":[[0,0],[0,0]],"v":[[-334.946,163.95],[333.807,163.95]],"c":false}]},{"t":217,"s":[{"i":[[0,0],[0,0]],"o":[[0,0],[0,0]],"v":[[-421,166],[404,166]],"c":false}]}],"ix":2},"nm":"Path 1","mn":"ADBE Vector Shape - Group","hd":false},{"ty":"st","c":{"a":0,"k":[1,0.36862745098,0.392156862745,1],"ix":3},"o":{"a":0,"k":100,"ix":4},"w":{"a":1,"k":[{"i":{"x":[0.613],"y":[1]},"o":{"x":[0.276],"y":[0]},"t":30,"s":[35]},{"i":{"x":[0.682],"y":[1]},"o":{"x":[0.223],"y":[0]},"t":37,"s":[32]},{"i":{"x":[0.261],"y":[1]},"o":{"x":[0.735],"y":[0]},"t":136,"s":[32]},{"i":{"x":[0.667],"y":[1]},"o":{"x":[0.167],"y":[0]},"t":147,"s":[25]},{"i":{"x":[0.261],"y":[1]},"o":{"x":[0.735],"y":[0]},"t":206,"s":[25]},{"t":217,"s":[35]}],"ix":5},"lc":2,"lj":2,"bm":0,"nm":"Stroke 1","mn":"ADBE Vector Graphic - Stroke","hd":false},{"ty":"tr","p":{"a":0,"k":[0,0],"ix":2},"a":{"a":0,"k":[0,0],"ix":1},"s":{"a":0,"k":[100,100],"ix":3},"r":{"a":0,"k":0,"ix":6},"o":{"a":0,"k":100,"ix":7},"sk":{"a":0,"k":0,"ix":4},"sa":{"a":0,"k":0,"ix":5},"nm":"Transform"}],"nm":"Shape 1","np":2,"cix":2,"bm":0,"ix":1,"mn":"ADBE Vector Group","hd":false},{"ty":"tm","s":{"a":0,"k":0,"ix":1},"e":{"a":1,"k":[{"i":{"x":[0.667],"y":[1]},"o":{"x":[0.167],"y":[0.167]},"t":2,"s":[1]},{"i":{"x":[0.261],"y":[1]},"o":{"x":[0.735],"y":[0]},"t":136,"s":[100]},{"i":{"x":[0.833],"y":[1]},"o":{"x":[0.333],"y":[0]},"t":147,"s":[1]},{"i":{"x":[0.833],"y":[0.833]},"o":{"x":[0.163],"y":[0.146]},"t":148,"s":[1]},{"i":{"x":[0.634],"y":[0.624]},"o":{"x":[0.299],"y":[0.289]},"t":205,"s":[62.454]},{"i":{"x":[0.609],"y":[1.067]},"o":{"x":[0.27],"y":[-0.043]},"t":206,"s":[63.299]},{"i":{"x":[0.838],"y":[1]},"o":{"x":[0.281],"y":[0.092]},"t":217,"s":[4]},{"t":251,"s":[100]}],"ix":2},"o":{"a":0,"k":0,"ix":3},"m":1,"ix":2,"nm":"Trim Paths 1","mn":"ADBE Vector Filter - Trim","hd":false}],"ip":0,"op":217,"st":-142,"ct":1,"bm":0},{"ddd":0,"ind":9,"ty":4,"nm":"Shape5","parent":7,"sr":1,"ks":{"o":{"a":0,"k":100,"ix":11},"r":{"a":0,"k":0,"ix":10},"p":{"a":0,"k":[0,0,0],"ix":2,"l":2},"a":{"a":0,"k":[-60.319,50.569,0],"ix":1,"l":2},"s":{"a":1,"k":[{"i":{"x":[0.261,0.277,0.667],"y":[1,1,1]},"o":{"x":[0.735,0.727,0.333],"y":[0,0,0]},"t":30,"s":[100,100,100]},{"i":{"x":[0.667,0.667,0.667],"y":[1,1,1]},"o":{"x":[0.333,0.333,0.333],"y":[0,0,0]},"t":37,"s":[125,166,100]},{"i":{"x":[0.261,0.277,0.667],"y":[1,1,1]},"o":{"x":[0.735,0.727,0.333],"y":[0,0,0]},"t":64,"s":[125,166,100]},{"i":{"x":[0.667,0.667,0.667],"y":[1,1,1]},"o":{"x":[0.333,0.333,0.333],"y":[0,0,0]},"t":71,"s":[54,95,100]},{"i":{"x":[0.261,0.277,0.667],"y":[1,1,1]},"o":{"x":[0.735,0.727,0.333],"y":[0,0,0]},"t":99,"s":[54,95,100]},{"i":{"x":[0.261,0.277,0.667],"y":[1,1,1]},"o":{"x":[0.333,0.333,0.333],"y":[0,0,0]},"t":107,"s":[61,181,100]},{"i":{"x":[0.261,0.277,0.667],"y":[1,1,1]},"o":{"x":[0.167,0.167,0.167],"y":[0,0,0]},"t":136,"s":[58,100,100]},{"i":{"x":[0.667,0.667,0.667],"y":[1,1,1]},"o":{"x":[0.167,0.167,0.167],"y":[0,0,0]},"t":147,"s":[58,100,100]},{"i":{"x":[0.261,0.277,0.667],"y":[1,1,1]},"o":{"x":[0.735,0.727,0.333],"y":[0,0,0]},"t":206,"s":[58,100,100]},{"t":217,"s":[100,100,100]}],"ix":6,"l":2}},"ao":0,"ef":[{"ty":25,"nm":"Drop Shadow","np":8,"mn":"ADBE Drop Shadow","ix":1,"en":1,"ef":[{"ty":2,"nm":"Shadow Color","mn":"ADBE Drop Shadow-0001","ix":1,"v":{"a":0,"k":[0,0,0,1],"ix":1}},{"ty":0,"nm":"Opacity","mn":"ADBE Drop Shadow-0002","ix":2,"v":{"a":0,"k":55.5,"ix":2}},{"ty":0,"nm":"Direction","mn":"ADBE Drop Shadow-0003","ix":3,"v":{"a":0,"k":135,"ix":3}},{"ty":0,"nm":"Distance","mn":"ADBE Drop Shadow-0004","ix":4,"v":{"a":0,"k":4,"ix":4}},{"ty":0,"nm":"Softness","mn":"ADBE Drop Shadow-0005","ix":5,"v":{"a":0,"k":10,"ix":5}},{"ty":7,"nm":"Shadow Only","mn":"ADBE Drop Shadow-0006","ix":6,"v":{"a":0,"k":0,"ix":6}}]}],"shapes":[{"ty":"gr","it":[{"ty":"rc","d":1,"s":{"a":0,"k":[960,540],"ix":2},"p":{"a":1,"k":[{"t":0,"s":[0,0],"h":1},{"i":{"x":0.261,"y":0.261},"o":{"x":0.735,"y":0.735},"t":136,"s":[0,0],"to":[0,0],"ti":[0,0]},{"i":{"x":0.667,"y":0.667},"o":{"x":0.167,"y":0.167},"t":147,"s":[0,0],"to":[0,0],"ti":[0,0]},{"i":{"x":0.261,"y":0.261},"o":{"x":0.735,"y":0.735},"t":206,"s":[0,0],"to":[0,0],"ti":[0,0]},{"t":217,"s":[0,0]}],"ix":3},"r":{"a":0,"k":14,"ix":4},"nm":"Rectangle Path 1","mn":"ADBE Vector Shape - Rect","hd":false},{"ty":"fl","c":{"a":0,"k":[0,0.317647058824,0.454901990704,1],"ix":4},"o":{"a":0,"k":100,"ix":5},"r":1,"bm":0,"nm":"Fill 1","mn":"ADBE Vector Graphic - Fill","hd":false},{"ty":"tr","p":{"a":0,"k":[-60.319,50.569],"ix":2},"a":{"a":0,"k":[0,0],"ix":1},"s":{"a":0,"k":[100,100],"ix":3},"r":{"a":0,"k":0,"ix":6},"o":{"a":0,"k":100,"ix":7},"sk":{"a":0,"k":0,"ix":4},"sa":{"a":0,"k":0,"ix":5},"nm":"Transform"}],"nm":"Rectangle 1","np":3,"cix":2,"bm":0,"ix":1,"mn":"ADBE Vector Group","hd":false}],"ip":0,"op":217,"st":0,"ct":1,"bm":0},{"ddd":0,"ind":10,"ty":3,"nm":"Null 1","sr":1,"ks":{"o":{"a":0,"k":0,"ix":11},"r":{"a":0,"k":0,"ix":10},"p":{"a":1,"k":[{"i":{"x":0.261,"y":1},"o":{"x":0.735,"y":0},"t":136,"s":[960,720,0],"to":[-94.783,53.167,0],"ti":[94.783,-53.167,0]},{"i":{"x":0.667,"y":0.667},"o":{"x":0.167,"y":0.167},"t":147,"s":[391.3,1039,0],"to":[0,0,0],"ti":[0,0,0]},{"i":{"x":0.261,"y":1},"o":{"x":0.735,"y":0},"t":206,"s":[391.3,1039,0],"to":[94.783,-53.167,0],"ti":[-94.783,53.167,0]},{"t":217,"s":[960,720,0]}],"ix":2,"l":2},"a":{"a":0,"k":[0,0,0],"ix":1,"l":2},"s":{"a":1,"k":[{"i":{"x":[0.261,0.277,0.667],"y":[1,1,1]},"o":{"x":[0.735,0.727,0.333],"y":[0,0,0]},"t":136,"s":[110,110,100]},{"i":{"x":[0.667,0.667,0.667],"y":[1,1,1]},"o":{"x":[0.167,0.167,0.167],"y":[0,0,0]},"t":147,"s":[79.2,79.2,100]},{"i":{"x":[0.261,0.277,0.667],"y":[1,1,1]},"o":{"x":[0.735,0.727,0.333],"y":[0,0,0]},"t":206,"s":[79.2,79.2,100]},{"t":217,"s":[110,110,100]}],"ix":6,"l":2}},"ao":0,"ip":0,"op":217,"st":0,"bm":0},{"ddd":0,"ind":11,"ty":4,"nm":"Bar6","parent":12,"sr":1,"ks":{"o":{"a":0,"k":100,"ix":11},"r":{"a":0,"k":0,"ix":10},"p":{"a":1,"k":[{"i":{"x":0.261,"y":1},"o":{"x":0.735,"y":0},"t":30,"s":[-60.319,267.694,0],"to":[0,2.906,0],"ti":[0,-2.906,0]},{"i":{"x":0.667,"y":0.667},"o":{"x":0.333,"y":0.333},"t":37,"s":[-60.319,285.128,0],"to":[0,0,0],"ti":[0,0,0]},{"i":{"x":0.261,"y":1},"o":{"x":0.735,"y":0},"t":64,"s":[-60.319,285.128,0],"to":[0,-1.93,0],"ti":[0,1.93,0]},{"i":{"x":0.667,"y":0.667},"o":{"x":0.333,"y":0.333},"t":71,"s":[-60.319,273.549,0],"to":[0,0,0],"ti":[0,0,0]},{"i":{"x":0.261,"y":1},"o":{"x":0.735,"y":0},"t":99,"s":[-60.319,273.549,0],"to":[0,3.167,0],"ti":[0,-3.167,0]},{"i":{"x":0.667,"y":0.667},"o":{"x":0.333,"y":0.333},"t":107,"s":[-60.319,292.549,0],"to":[0,0,0],"ti":[0,0,0]},{"i":{"x":0.261,"y":1},"o":{"x":0.735,"y":0},"t":136,"s":[-60.319,292.549,0],"to":[-1.5,-3.5,0],"ti":[1.5,3.5,0]},{"i":{"x":0.667,"y":0.667},"o":{"x":0.167,"y":0.167},"t":147,"s":[-69.319,271.549,0],"to":[0,0,0],"ti":[0,0,0]},{"i":{"x":0.261,"y":1},"o":{"x":0.735,"y":0},"t":206,"s":[-69.319,271.549,0],"to":[1.5,-0.642,0],"ti":[-1.5,0.642,0]},{"t":217,"s":[-60.319,267.694,0]}],"ix":2,"l":2},"a":{"a":0,"k":[-8.5,166.125,0],"ix":1,"l":2},"s":{"a":1,"k":[{"i":{"x":[0.261,0.277,0.667],"y":[1,1,1]},"o":{"x":[0.735,0.719,0.333],"y":[0,0,0]},"t":30,"s":[100,100,100]},{"i":{"x":[0.667,0.667,0.667],"y":[1,1,1]},"o":{"x":[0.333,0.333,0.333],"y":[0,0,0]},"t":37,"s":[82,64,100]},{"i":{"x":[0.261,0.277,0.667],"y":[1,1,1]},"o":{"x":[0.735,0.727,0.333],"y":[0,0,0]},"t":64,"s":[82,64,100]},{"i":{"x":[0.667,0.667,0.667],"y":[1,1,1]},"o":{"x":[0.333,0.333,0.333],"y":[0,0,0]},"t":71,"s":[122,73,100]},{"i":{"x":[0.261,0.277,0.667],"y":[1,1,1]},"o":{"x":[0.735,0.727,0.333],"y":[0,0,0]},"t":99,"s":[122,73,100]},{"i":{"x":[0.667,0.667,0.667],"y":[1,1,1]},"o":{"x":[0.333,0.333,0.333],"y":[0,0,0]},"t":107,"s":[122,42,100]},{"i":{"x":[0.261,0.277,0.667],"y":[1,1,1]},"o":{"x":[0.735,0.727,0.333],"y":[0,0,0]},"t":136,"s":[122,42,100]},{"i":{"x":[0.667,0.667,0.667],"y":[1,1,1]},"o":{"x":[0.167,0.167,0.167],"y":[0,0,0]},"t":147,"s":[124,124,100]},{"i":{"x":[0.261,0.277,0.667],"y":[1,1,1]},"o":{"x":[0.735,0.727,0.333],"y":[0,0,0]},"t":206,"s":[124,124,100]},{"t":217,"s":[100,100,100]}],"ix":6,"l":2}},"ao":0,"shapes":[{"ty":"gr","it":[{"ind":0,"ty":"sh","ix":1,"ks":{"a":1,"k":[{"i":{"x":0.849,"y":1},"o":{"x":0.167,"y":0.167},"t":2,"s":[{"i":[[0,0],[0,0]],"o":[[0,0],[0,0]],"v":[[-421,166],[404,166]],"c":false}]},{"i":{"x":0.261,"y":1},"o":{"x":0.735,"y":0},"t":30,"s":[{"i":[[0,0],[0,0]],"o":[[0,0],[0,0]],"v":[[-421,166],[404,166]],"c":false}]},{"i":{"x":0.667,"y":1},"o":{"x":0.333,"y":0},"t":37,"s":[{"i":[[0,0],[0,0]],"o":[[0,0],[0,0]],"v":[[-538.256,164.222],[525.394,164.222]],"c":false}]},{"i":{"x":0.261,"y":1},"o":{"x":0.735,"y":0},"t":64,"s":[{"i":[[0,0],[0,0]],"o":[[0,0],[0,0]],"v":[[-538.256,164.222],[525.394,164.222]],"c":false}]},{"i":{"x":0.667,"y":1},"o":{"x":0.333,"y":0},"t":71,"s":[{"i":[[0,0],[0,0]],"o":[[0,0],[0,0]],"v":[[-334.946,163.95],[333.807,163.95]],"c":false}]},{"i":{"x":0.261,"y":1},"o":{"x":0.735,"y":0},"t":206,"s":[{"i":[[0,0],[0,0]],"o":[[0,0],[0,0]],"v":[[-334.946,163.95],[333.807,163.95]],"c":false}]},{"t":217,"s":[{"i":[[0,0],[0,0]],"o":[[0,0],[0,0]],"v":[[-421,166],[404,166]],"c":false}]}],"ix":2},"nm":"Path 1","mn":"ADBE Vector Shape - Group","hd":false},{"ty":"st","c":{"a":0,"k":[1,0.36862745098,0.392156862745,1],"ix":3},"o":{"a":0,"k":100,"ix":4},"w":{"a":1,"k":[{"i":{"x":[0.613],"y":[1]},"o":{"x":[0.276],"y":[0]},"t":30,"s":[35]},{"i":{"x":[0.682],"y":[1]},"o":{"x":[0.223],"y":[0]},"t":37,"s":[32]},{"i":{"x":[0.261],"y":[1]},"o":{"x":[0.735],"y":[0]},"t":136,"s":[32]},{"i":{"x":[0.667],"y":[1]},"o":{"x":[0.167],"y":[0]},"t":147,"s":[25]},{"i":{"x":[0.261],"y":[1]},"o":{"x":[0.735],"y":[0]},"t":206,"s":[25]},{"t":217,"s":[35]}],"ix":5},"lc":2,"lj":2,"bm":0,"nm":"Stroke 1","mn":"ADBE Vector Graphic - Stroke","hd":false},{"ty":"tr","p":{"a":0,"k":[0,0],"ix":2},"a":{"a":0,"k":[0,0],"ix":1},"s":{"a":0,"k":[100,100],"ix":3},"r":{"a":0,"k":0,"ix":6},"o":{"a":0,"k":100,"ix":7},"sk":{"a":0,"k":0,"ix":4},"sa":{"a":0,"k":0,"ix":5},"nm":"Transform"}],"nm":"Shape 1","np":2,"cix":2,"bm":0,"ix":1,"mn":"ADBE Vector Group","hd":false},{"ty":"tm","s":{"a":0,"k":0,"ix":1},"e":{"a":1,"k":[{"i":{"x":[0.667],"y":[1]},"o":{"x":[0.167],"y":[0.167]},"t":2,"s":[1]},{"i":{"x":[0.261],"y":[1]},"o":{"x":[0.735],"y":[0]},"t":136,"s":[100]},{"i":{"x":[0.833],"y":[1]},"o":{"x":[0.333],"y":[0]},"t":147,"s":[1]},{"i":{"x":[0.833],"y":[0.833]},"o":{"x":[0.163],"y":[0.146]},"t":148,"s":[1]},{"i":{"x":[0.634],"y":[0.624]},"o":{"x":[0.299],"y":[0.289]},"t":205,"s":[62.454]},{"i":{"x":[0.609],"y":[1.067]},"o":{"x":[0.27],"y":[-0.043]},"t":206,"s":[63.299]},{"i":{"x":[0.838],"y":[1]},"o":{"x":[0.281],"y":[0.092]},"t":217,"s":[4]},{"t":251,"s":[100]}],"ix":2},"o":{"a":0,"k":0,"ix":3},"m":1,"ix":2,"nm":"Trim Paths 1","mn":"ADBE Vector Filter - Trim","hd":false}],"ip":0,"op":217,"st":-142,"ct":1,"bm":0},{"ddd":0,"ind":12,"ty":4,"nm":"Shape6","parent":10,"sr":1,"ks":{"o":{"a":0,"k":100,"ix":11},"r":{"a":0,"k":0,"ix":10},"p":{"a":0,"k":[0,0,0],"ix":2,"l":2},"a":{"a":0,"k":[-60.319,50.569,0],"ix":1,"l":2},"s":{"a":1,"k":[{"i":{"x":[0.261,0.277,0.667],"y":[1,1,1]},"o":{"x":[0.735,0.727,0.333],"y":[0,0,0]},"t":30,"s":[100,100,100]},{"i":{"x":[0.667,0.667,0.667],"y":[1,1,1]},"o":{"x":[0.333,0.333,0.333],"y":[0,0,0]},"t":37,"s":[125,166,100]},{"i":{"x":[0.261,0.277,0.667],"y":[1,1,1]},"o":{"x":[0.735,0.727,0.333],"y":[0,0,0]},"t":64,"s":[125,166,100]},{"i":{"x":[0.667,0.667,0.667],"y":[1,1,1]},"o":{"x":[0.333,0.333,0.333],"y":[0,0,0]},"t":71,"s":[54,95,100]},{"i":{"x":[0.261,0.277,0.667],"y":[1,1,1]},"o":{"x":[0.735,0.727,0.333],"y":[0,0,0]},"t":99,"s":[54,95,100]},{"i":{"x":[0.667,0.667,0.667],"y":[1,1,1]},"o":{"x":[0.333,0.333,0.333],"y":[0,0,0]},"t":107,"s":[61,181,100]},{"i":{"x":[0.261,0.277,0.667],"y":[1,1,1]},"o":{"x":[0.735,0.727,0.333],"y":[0,0,0]},"t":136,"s":[61,181,100]},{"i":{"x":[0.667,0.667,0.667],"y":[1,1,1]},"o":{"x":[0.167,0.167,0.167],"y":[0,0,0]},"t":147,"s":[100,100,100]},{"i":{"x":[0.261,0.277,0.667],"y":[1,1,1]},"o":{"x":[0.735,0.727,0.333],"y":[0,0,0]},"t":206,"s":[100,100,100]},{"t":217,"s":[100,100,100]}],"ix":6,"l":2}},"ao":0,"ef":[{"ty":25,"nm":"Drop Shadow","np":8,"mn":"ADBE Drop Shadow","ix":1,"en":1,"ef":[{"ty":2,"nm":"Shadow Color","mn":"ADBE Drop Shadow-0001","ix":1,"v":{"a":0,"k":[0,0,0,1],"ix":1}},{"ty":0,"nm":"Opacity","mn":"ADBE Drop Shadow-0002","ix":2,"v":{"a":0,"k":55.5,"ix":2}},{"ty":0,"nm":"Direction","mn":"ADBE Drop Shadow-0003","ix":3,"v":{"a":0,"k":135,"ix":3}},{"ty":0,"nm":"Distance","mn":"ADBE Drop Shadow-0004","ix":4,"v":{"a":0,"k":4,"ix":4}},{"ty":0,"nm":"Softness","mn":"ADBE Drop Shadow-0005","ix":5,"v":{"a":0,"k":10,"ix":5}},{"ty":7,"nm":"Shadow Only","mn":"ADBE Drop Shadow-0006","ix":6,"v":{"a":0,"k":0,"ix":6}}]}],"shapes":[{"ty":"gr","it":[{"ty":"rc","d":1,"s":{"a":0,"k":[960,540],"ix":2},"p":{"a":1,"k":[{"t":0,"s":[0,0],"h":1},{"i":{"x":0.261,"y":0.261},"o":{"x":0.735,"y":0.735},"t":136,"s":[0,0],"to":[0,0],"ti":[0,0]},{"i":{"x":0.667,"y":0.667},"o":{"x":0.167,"y":0.167},"t":147,"s":[0,0],"to":[0,0],"ti":[0,0]},{"i":{"x":0.261,"y":0.261},"o":{"x":0.735,"y":0.735},"t":206,"s":[0,0],"to":[0,0],"ti":[0,0]},{"t":217,"s":[0,0]}],"ix":3},"r":{"a":0,"k":14,"ix":4},"nm":"Rectangle Path 1","mn":"ADBE Vector Shape - Rect","hd":false},{"ty":"fl","c":{"a":0,"k":[0,0.317647058824,0.454901990704,1],"ix":4},"o":{"a":0,"k":100,"ix":5},"r":1,"bm":0,"nm":"Fill 1","mn":"ADBE Vector Graphic - Fill","hd":false},{"ty":"tr","p":{"a":0,"k":[-60.319,50.569],"ix":2},"a":{"a":0,"k":[0,0],"ix":1},"s":{"a":0,"k":[100,100],"ix":3},"r":{"a":0,"k":0,"ix":6},"o":{"a":0,"k":100,"ix":7},"sk":{"a":0,"k":0,"ix":4},"sa":{"a":0,"k":0,"ix":5},"nm":"Transform"}],"nm":"Rectangle 1","np":3,"cix":2,"bm":0,"ix":1,"mn":"ADBE Vector Group","hd":false}],"ip":0,"op":217,"st":0,"ct":1,"bm":0},{"ddd":0,"ind":13,"ty":3,"nm":"Null 1","sr":1,"ks":{"o":{"a":0,"k":0,"ix":11},"r":{"a":0,"k":0,"ix":10},"p":{"a":1,"k":[{"i":{"x":0.261,"y":1},"o":{"x":0.735,"y":0},"t":136,"s":[960,720,0],"to":[74.067,-59.033,0],"ti":[-74.067,59.033,0]},{"i":{"x":0.667,"y":0.667},"o":{"x":0.167,"y":0.167},"t":147,"s":[1404.4,365.8,0],"to":[0,0,0],"ti":[0,0,0]},{"i":{"x":0.261,"y":1},"o":{"x":0.735,"y":0},"t":206,"s":[1404.4,365.8,0],"to":[-74.067,59.033,0],"ti":[74.067,-59.033,0]},{"t":217,"s":[960,720,0]}],"ix":2,"l":2},"a":{"a":0,"k":[0,0,0],"ix":1,"l":2},"s":{"a":1,"k":[{"i":{"x":[0.261,0.277,0.667],"y":[1,1,1]},"o":{"x":[0.735,0.727,0.333],"y":[0,0,0]},"t":136,"s":[110,110,100]},{"i":{"x":[0.667,0.667,0.667],"y":[1,1,1]},"o":{"x":[0.167,0.167,0.167],"y":[0,0,0]},"t":147,"s":[71.5,71.5,100]},{"i":{"x":[0.261,0.277,0.667],"y":[1,1,1]},"o":{"x":[0.735,0.727,0.333],"y":[0,0,0]},"t":206,"s":[71.5,71.5,100]},{"t":217,"s":[110,110,100]}],"ix":6,"l":2}},"ao":0,"ip":0,"op":217,"st":0,"bm":0},{"ddd":0,"ind":14,"ty":4,"nm":"Bar2","parent":15,"sr":1,"ks":{"o":{"a":0,"k":100,"ix":11},"r":{"a":0,"k":0,"ix":10},"p":{"a":1,"k":[{"i":{"x":0.261,"y":1},"o":{"x":0.735,"y":0},"t":30,"s":[-60.319,267.694,0],"to":[0,2.906,0],"ti":[0,-2.906,0]},{"i":{"x":0.667,"y":0.667},"o":{"x":0.333,"y":0.333},"t":37,"s":[-60.319,285.128,0],"to":[0,0,0],"ti":[0,0,0]},{"i":{"x":0.261,"y":1},"o":{"x":0.735,"y":0},"t":64,"s":[-60.319,285.128,0],"to":[0,-1.93,0],"ti":[0,1.93,0]},{"i":{"x":0.667,"y":0.667},"o":{"x":0.333,"y":0.333},"t":71,"s":[-60.319,273.549,0],"to":[0,0,0],"ti":[0,0,0]},{"i":{"x":0.261,"y":1},"o":{"x":0.735,"y":0},"t":99,"s":[-60.319,273.549,0],"to":[0,3.167,0],"ti":[0,-3.167,0]},{"i":{"x":0.667,"y":0.667},"o":{"x":0.333,"y":0.333},"t":107,"s":[-60.319,292.549,0],"to":[0,0,0],"ti":[0,0,0]},{"i":{"x":0.261,"y":1},"o":{"x":0.735,"y":0},"t":136,"s":[-60.319,292.549,0],"to":[-1.5,-3.5,0],"ti":[1.5,3.5,0]},{"i":{"x":0.667,"y":0.667},"o":{"x":0.167,"y":0.167},"t":147,"s":[-69.319,271.549,0],"to":[0,0,0],"ti":[0,0,0]},{"i":{"x":0.261,"y":1},"o":{"x":0.735,"y":0},"t":206,"s":[-69.319,271.549,0],"to":[1.5,-0.642,0],"ti":[-1.5,0.642,0]},{"t":217,"s":[-60.319,267.694,0]}],"ix":2,"l":2},"a":{"a":0,"k":[-8.5,166.125,0],"ix":1,"l":2},"s":{"a":1,"k":[{"i":{"x":[0.261,0.277,0.667],"y":[1,1,1]},"o":{"x":[0.735,0.719,0.333],"y":[0,0,0]},"t":30,"s":[100,100,100]},{"i":{"x":[0.667,0.667,0.667],"y":[1,1,1]},"o":{"x":[0.333,0.333,0.333],"y":[0,0,0]},"t":37,"s":[82,64,100]},{"i":{"x":[0.261,0.277,0.667],"y":[1,1,1]},"o":{"x":[0.735,0.727,0.333],"y":[0,0,0]},"t":64,"s":[82,64,100]},{"i":{"x":[0.667,0.667,0.667],"y":[1,1,1]},"o":{"x":[0.333,0.333,0.333],"y":[0,0,0]},"t":71,"s":[122,73,100]},{"i":{"x":[0.261,0.277,0.667],"y":[1,1,1]},"o":{"x":[0.735,0.727,0.333],"y":[0,0,0]},"t":99,"s":[122,73,100]},{"i":{"x":[0.667,0.667,0.667],"y":[1,1,1]},"o":{"x":[0.333,0.333,0.333],"y":[0,0,0]},"t":107,"s":[122,42,100]},{"i":{"x":[0.261,0.277,0.667],"y":[1,1,1]},"o":{"x":[0.735,0.727,0.333],"y":[0,0,0]},"t":136,"s":[122,42,100]},{"i":{"x":[0.667,0.667,0.667],"y":[1,1,1]},"o":{"x":[0.167,0.167,0.167],"y":[0,0,0]},"t":147,"s":[124,123,100]},{"i":{"x":[0.261,0.277,0.667],"y":[1,1,1]},"o":{"x":[0.735,0.727,0.333],"y":[0,0,0]},"t":206,"s":[124,123,100]},{"t":217,"s":[100,100,100]}],"ix":6,"l":2}},"ao":0,"shapes":[{"ty":"gr","it":[{"ind":0,"ty":"sh","ix":1,"ks":{"a":1,"k":[{"i":{"x":0.849,"y":1},"o":{"x":0.167,"y":0.167},"t":2,"s":[{"i":[[0,0],[0,0]],"o":[[0,0],[0,0]],"v":[[-421,166],[404,166]],"c":false}]},{"i":{"x":0.261,"y":1},"o":{"x":0.735,"y":0},"t":30,"s":[{"i":[[0,0],[0,0]],"o":[[0,0],[0,0]],"v":[[-421,166],[404,166]],"c":false}]},{"i":{"x":0.667,"y":1},"o":{"x":0.333,"y":0},"t":37,"s":[{"i":[[0,0],[0,0]],"o":[[0,0],[0,0]],"v":[[-538.256,164.222],[525.394,164.222]],"c":false}]},{"i":{"x":0.261,"y":1},"o":{"x":0.735,"y":0},"t":64,"s":[{"i":[[0,0],[0,0]],"o":[[0,0],[0,0]],"v":[[-538.256,164.222],[525.394,164.222]],"c":false}]},{"i":{"x":0.667,"y":1},"o":{"x":0.333,"y":0},"t":71,"s":[{"i":[[0,0],[0,0]],"o":[[0,0],[0,0]],"v":[[-334.946,163.95],[333.807,163.95]],"c":false}]},{"i":{"x":0.261,"y":1},"o":{"x":0.735,"y":0},"t":206,"s":[{"i":[[0,0],[0,0]],"o":[[0,0],[0,0]],"v":[[-334.946,163.95],[333.807,163.95]],"c":false}]},{"t":217,"s":[{"i":[[0,0],[0,0]],"o":[[0,0],[0,0]],"v":[[-421,166],[404,166]],"c":false}]}],"ix":2},"nm":"Path 1","mn":"ADBE Vector Shape - Group","hd":false},{"ty":"st","c":{"a":0,"k":[1,0.36862745098,0.392156862745,1],"ix":3},"o":{"a":0,"k":100,"ix":4},"w":{"a":1,"k":[{"i":{"x":[0.613],"y":[1]},"o":{"x":[0.276],"y":[0]},"t":30,"s":[35]},{"i":{"x":[0.682],"y":[1]},"o":{"x":[0.223],"y":[0]},"t":37,"s":[32]},{"i":{"x":[0.261],"y":[1]},"o":{"x":[0.735],"y":[0]},"t":136,"s":[32]},{"i":{"x":[0.667],"y":[1]},"o":{"x":[0.167],"y":[0]},"t":147,"s":[25]},{"i":{"x":[0.261],"y":[1]},"o":{"x":[0.735],"y":[0]},"t":206,"s":[25]},{"t":217,"s":[35]}],"ix":5},"lc":2,"lj":2,"bm":0,"nm":"Stroke 1","mn":"ADBE Vector Graphic - Stroke","hd":false},{"ty":"tr","p":{"a":0,"k":[0,0],"ix":2},"a":{"a":0,"k":[0,0],"ix":1},"s":{"a":0,"k":[100,100],"ix":3},"r":{"a":0,"k":0,"ix":6},"o":{"a":0,"k":100,"ix":7},"sk":{"a":0,"k":0,"ix":4},"sa":{"a":0,"k":0,"ix":5},"nm":"Transform"}],"nm":"Shape 1","np":2,"cix":2,"bm":0,"ix":1,"mn":"ADBE Vector Group","hd":false},{"ty":"tm","s":{"a":0,"k":0,"ix":1},"e":{"a":1,"k":[{"i":{"x":[0.667],"y":[1]},"o":{"x":[0.167],"y":[0.167]},"t":2,"s":[1]},{"i":{"x":[0.261],"y":[1]},"o":{"x":[0.735],"y":[0]},"t":136,"s":[100]},{"i":{"x":[0.833],"y":[1]},"o":{"x":[0.333],"y":[0]},"t":147,"s":[1]},{"i":{"x":[0.833],"y":[0.833]},"o":{"x":[0.163],"y":[0.146]},"t":148,"s":[1]},{"i":{"x":[0.634],"y":[0.624]},"o":{"x":[0.299],"y":[0.289]},"t":205,"s":[62.454]},{"i":{"x":[0.609],"y":[1.067]},"o":{"x":[0.27],"y":[-0.043]},"t":206,"s":[63.299]},{"i":{"x":[0.838],"y":[1]},"o":{"x":[0.281],"y":[0.092]},"t":217,"s":[4]},{"t":251,"s":[100]}],"ix":2},"o":{"a":0,"k":0,"ix":3},"m":1,"ix":2,"nm":"Trim Paths 1","mn":"ADBE Vector Filter - Trim","hd":false}],"ip":0,"op":217,"st":-142,"ct":1,"bm":0},{"ddd":0,"ind":15,"ty":4,"nm":"Shape2","parent":13,"sr":1,"ks":{"o":{"a":0,"k":100,"ix":11},"r":{"a":0,"k":0,"ix":10},"p":{"a":0,"k":[0,0,0],"ix":2,"l":2},"a":{"a":0,"k":[-60.319,50.569,0],"ix":1,"l":2},"s":{"a":1,"k":[{"i":{"x":[0.261,0.277,0.667],"y":[1,1,1]},"o":{"x":[0.735,0.727,0.333],"y":[0,0,0]},"t":30,"s":[100,100,100]},{"i":{"x":[0.667,0.667,0.667],"y":[1,1,1]},"o":{"x":[0.333,0.333,0.333],"y":[0,0,0]},"t":37,"s":[125,166,100]},{"i":{"x":[0.261,0.277,0.667],"y":[1,1,1]},"o":{"x":[0.735,0.727,0.333],"y":[0,0,0]},"t":64,"s":[125,166,100]},{"i":{"x":[0.667,0.667,0.667],"y":[1,1,1]},"o":{"x":[0.333,0.333,0.333],"y":[0,0,0]},"t":71,"s":[54,95,100]},{"i":{"x":[0.261,0.277,0.667],"y":[1,1,1]},"o":{"x":[0.735,0.727,0.333],"y":[0,0,0]},"t":99,"s":[54,95,100]},{"i":{"x":[0.667,0.667,0.667],"y":[1,1,1]},"o":{"x":[0.333,0.333,0.333],"y":[0,0,0]},"t":107,"s":[61,181,100]},{"i":{"x":[0.261,0.277,0.667],"y":[1,1,1]},"o":{"x":[0.735,0.727,0.333],"y":[0,0,0]},"t":136,"s":[61,181,100]},{"i":{"x":[0.667,0.667,0.667],"y":[1,1,1]},"o":{"x":[0.167,0.167,0.167],"y":[0,0,0]},"t":147,"s":[100,100,100]},{"i":{"x":[0.261,0.277,0.667],"y":[1,1,1]},"o":{"x":[0.735,0.727,0.333],"y":[0,0,0]},"t":206,"s":[100,100,100]},{"t":217,"s":[100,100,100]}],"ix":6,"l":2}},"ao":0,"ef":[{"ty":25,"nm":"Drop Shadow","np":8,"mn":"ADBE Drop Shadow","ix":1,"en":1,"ef":[{"ty":2,"nm":"Shadow Color","mn":"ADBE Drop Shadow-0001","ix":1,"v":{"a":0,"k":[0,0,0,1],"ix":1}},{"ty":0,"nm":"Opacity","mn":"ADBE Drop Shadow-0002","ix":2,"v":{"a":0,"k":55.5,"ix":2}},{"ty":0,"nm":"Direction","mn":"ADBE Drop Shadow-0003","ix":3,"v":{"a":0,"k":135,"ix":3}},{"ty":0,"nm":"Distance","mn":"ADBE Drop Shadow-0004","ix":4,"v":{"a":0,"k":4,"ix":4}},{"ty":0,"nm":"Softness","mn":"ADBE Drop Shadow-0005","ix":5,"v":{"a":0,"k":10,"ix":5}},{"ty":7,"nm":"Shadow Only","mn":"ADBE Drop Shadow-0006","ix":6,"v":{"a":0,"k":0,"ix":6}}]}],"shapes":[{"ty":"gr","it":[{"ty":"rc","d":1,"s":{"a":0,"k":[960,540],"ix":2},"p":{"a":1,"k":[{"t":0,"s":[0,0],"h":1},{"i":{"x":0.261,"y":0.261},"o":{"x":0.735,"y":0.735},"t":136,"s":[0,0],"to":[0,0],"ti":[0,0]},{"i":{"x":0.667,"y":0.667},"o":{"x":0.167,"y":0.167},"t":147,"s":[0,0],"to":[0,0],"ti":[0,0]},{"i":{"x":0.261,"y":0.261},"o":{"x":0.735,"y":0.735},"t":206,"s":[0,0],"to":[0,0],"ti":[0,0]},{"t":217,"s":[0,0]}],"ix":3},"r":{"a":0,"k":14,"ix":4},"nm":"Rectangle Path 1","mn":"ADBE Vector Shape - Rect","hd":false},{"ty":"fl","c":{"a":0,"k":[0,0.317647058824,0.454901990704,1],"ix":4},"o":{"a":0,"k":100,"ix":5},"r":1,"bm":0,"nm":"Fill 1","mn":"ADBE Vector Graphic - Fill","hd":false},{"ty":"tr","p":{"a":0,"k":[-60.319,50.569],"ix":2},"a":{"a":0,"k":[0,0],"ix":1},"s":{"a":0,"k":[100,100],"ix":3},"r":{"a":0,"k":0,"ix":6},"o":{"a":0,"k":100,"ix":7},"sk":{"a":0,"k":0,"ix":4},"sa":{"a":0,"k":0,"ix":5},"nm":"Transform"}],"nm":"Rectangle 1","np":3,"cix":2,"bm":0,"ix":1,"mn":"ADBE Vector Group","hd":false}],"ip":0,"op":217,"st":0,"ct":1,"bm":0}],"markers":[]}